makefig/__init__.py
makefig/config.py
makefig/construct_figure.py
makefig/format_axis.py
makefig/pvals.py
tests/__init__.py
tests/tests/__init__.py
tests/tests/test_integration/__init__.py
tests/tests/test_unit/__init__.py
makefig-0.0.1rc0.dist-info/LICENSE
makefig-0.0.1rc0.dist-info/METADATA
makefig-0.0.1rc0.dist-info/WHEEL
makefig-0.0.1rc0.dist-info/top_level.txt
makefig-0.0.1rc0.dist-info/RECORD
